[
  {
    "question": "Какой цвет получается при смешивании всех цветов света?",
    "options": ["Черный", "Красный", "Белый", "Серый"],
    "correct_answer": 2,
    "difficulty": 1
  },
  {
    "question": "Сколько лап у паука?",
    "options": ["6", "8", "10", "12"],
    "correct_answer": 1,
    "difficulty": 1
  },
  {
    "question": "Какой из этих персонажей — пират?",
    "options": ["Спанч Боб", "Капитан Джек Воробей", "Шрек", "Микки Маус"],
    "correct_answer": 1,
    "difficulty": 1
  },
  {
    "question": "Какой месяц является последним в году?",
    "options": ["Ноябрь", "Декабрь", "Январь", "Октябрь"],
    "correct_answer": 1,
    "difficulty": 1
  },
  {
    "question": "Какой фрукт ассоциируется с Адамом и Евой?",
    "options": ["Груша", "Яблоко", "Апельсин", "Персик"],
    "correct_answer": 1,
    "difficulty": 1
  },
  {
    "question": "Какой из этих элементов является щелочным металлом?",
    "options": ["Кальций", "Натрий", "Магний", "Алюминий"],
    "correct_answer": 1,
    "difficulty": 2
  },
  {
    "question": "Как называется столица Германии?",
    "options": ["Мюнхен", "Гамбург", "Берлин", "Франкфурт"],
    "correct_answer": 2,
    "difficulty": 2
  },
  {
    "question": "Кто из этих ученых открыл закон всемирного тяготения?",
    "options": ["Галилей", "Ньютон", "Эйнштейн", "Кеплер"],
    "correct_answer": 1,
    "difficulty": 2
  },
  {
    "question": "Какой из этих языков является мертвым?",
    "options": ["Латинский", "Французский", "Испанский", "Английский"],
    "correct_answer": 0,
    "difficulty": 2
  },
  {
    "question": "Какой из этих процессов происходит в хлоропластах?",
    "options": ["Дыхание", "Фотосинтез", "Секреция", "Репликация"],
    "correct_answer": 1,
    "difficulty": 2
  },
  {
    "question": "Какой из этих терминов означает виртуализацию сети?",
    "options": ["VPN", "SDN", "DNS", "HTML"],
    "correct_answer": 1,
    "difficulty": 3
  },
  {
    "question": "Какой из этих языков программирования используется для разработки Android-приложений?",
    "options": ["Swift", "Kotlin", "PHP", "TypeScript"],
    "correct_answer": 1,
    "difficulty": 3
  },
  {
    "question": "Как называется процесс превращения газа в жидкость?",
    "options": ["Испарение", "Конденсация", "Сублимация", "Кристаллизация"],
    "correct_answer": 1,
    "difficulty": 3
  },
  {
    "question": "Какой из этих элементов имеет наименьшую атомную массу?",
    "options": ["Гелий", "Водород", "Литий", "Бериллий"],
    "correct_answer": 1,
    "difficulty": 3
  },
  {
    "question": "Какой из этих эффектов объясняет красное смещение в спектрах галактик?",
    "options": ["Гравитационное красное смещение", "Эффект Доплера", "Расширение Вселенной", "Интерференция"],
    "correct_answer": 2,
    "difficulty": 3
  }
]
